aiomusiccast/__init__.py
aiomusiccast/__main__.py
aiomusiccast/capabilities.py
aiomusiccast/capability_registry.py
aiomusiccast/const.py
aiomusiccast/exceptions.py
aiomusiccast/features.py
aiomusiccast/musiccast_data.py
aiomusiccast/musiccast_device.py
aiomusiccast/musiccast_media_content.py
aiomusiccast/pyamaha.py
aiomusiccast-0.15.0.dist-info/METADATA
aiomusiccast-0.15.0.dist-info/WHEEL
aiomusiccast-0.15.0.dist-info/licenses/LICENSE.md
aiomusiccast-0.15.0.dist-info/RECORD
