Metadata-Version: 2.4
Name: aiomusiccast
Version: 0.15.0
Summary: Companion library for musiccast devices intended for the Home Assistant integration.
Project-URL: Homepage, https://pypi.org/project/aiomusiccast
Project-URL: Documentation, https://aiomusiccast.readthedocs.io
Project-URL: Repository, https://github.com/vigonotion/aiomusiccast
Author-email: Tom Schneider <mail@vigonotion.com>
License: **The MIT License (MIT)**
License-File: LICENSE.md
Classifier: Development Status :: 1 - Planning
Classifier: Natural Language :: English
Classifier: Operating System :: OS Independent
Classifier: Programming Language :: Python
Classifier: Programming Language :: Python :: 3 :: Only
Classifier: Programming Language :: Python :: 3.10
Classifier: Programming Language :: Python :: 3.11
Classifier: Programming Language :: Python :: 3.12
Classifier: Programming Language :: Python :: 3.13
Classifier: Programming Language :: Python :: 3.14
Requires-Python: >=3.10
Requires-Dist: aiohttp>=3.9
